setup.py
motionTracker/__init__.py
motionTracker/ball.py
motionTracker/medium.py
motionTracker/motionTracker.py
motionTracker/python_code.py
motion_tracking.egg-info/PKG-INFO
motion_tracking.egg-info/SOURCES.txt
motion_tracking.egg-info/dependency_links.txt
motion_tracking.egg-info/not-zip-safe
motion_tracking.egg-info/top_level.txt