Metadata-Version: 1.0
Name: motion-tracking
Version: 0.1
Summary: Projectile Motion Tracker
Home-page: UNKNOWN
Author: UNKNOWN
Author-email: UNKNOWN
License: UNKNOWN
Platform: UNKNOWN
